Metadata-Version: 2.1
Name: pylint-pa
Version: 3.0.0b1
Summary: python code static checker, but passive-aggressive
Author-email: Python Code Quality Authority <code-quality@python.org>
License: GPL-2.0-or-later
Project-URL: Docs: User Guide, https://pylint.readthedocs.io/en/latest/
Project-URL: Source Code, https://github.com/pylint-dev/pylint
Project-URL: homepage, https://github.com/pylint-dev/pylint
Project-URL: What's New, https://pylint.readthedocs.io/en/latest/whatsnew/2/
Project-URL: Bug Tracker, https://github.com/pylint-dev/pylint/issues
Project-URL: Discord Server, https://discord.com/invite/Egy6P8AMB5
Project-URL: Docs: Contributor Guide, https://pylint.readthedocs.io/en/latest/development_guide/contributor_guide/index.html
Keywords: static code analysis,linter,python,lint
Classifier: Development Status :: 6 - Mature
Classifier: Environment :: Console
Classifier: Intended Audience :: Developers
Classifier: License :: OSI Approved :: GNU General Public License v2 (GPLv2)
Classifier: Operating System :: OS Independent
Classifier: Programming Language :: Python
Classifier: Programming Language :: Python :: 3
Classifier: Programming Language :: Python :: 3 :: Only
Classifier: Programming Language :: Python :: 3.8
Classifier: Programming Language :: Python :: 3.9
Classifier: Programming Language :: Python :: 3.10
Classifier: Programming Language :: Python :: 3.11
Classifier: Programming Language :: Python :: Implementation :: CPython
Classifier: Programming Language :: Python :: Implementation :: PyPy
Classifier: Topic :: Software Development :: Debuggers
Classifier: Topic :: Software Development :: Quality Assurance
Classifier: Topic :: Software Development :: Testing
Classifier: Typing :: Typed
Requires-Python: >=3.8.0
License-File: LICENSE
License-File: CONTRIBUTORS.txt
Requires-Dist: platformdirs (>=2.2.0)
Requires-Dist: astroid (<=3.1.0-dev0,>=3.0.0a7)
Requires-Dist: isort (<6,>=4.2.5)
Requires-Dist: mccabe (<0.8,>=0.6)
Requires-Dist: tomlkit (>=0.10.1)
Requires-Dist: typing-extensions (>=3.10.0) ; python_version < "3.10"
Requires-Dist: dill (>=0.2) ; python_version < "3.11"
Requires-Dist: tomli (>=1.1.0) ; python_version < "3.11"
Requires-Dist: dill (>=0.3.6) ; python_version >= "3.11"
Requires-Dist: colorama (>=0.4.5) ; sys_platform == "win32"
Provides-Extra: spelling
Requires-Dist: pyenchant (~=3.2) ; extra == 'spelling'
Provides-Extra: testutils
Requires-Dist: gitpython (>3) ; extra == 'testutils'
